chapter4/example4-1/example4-1.sv
module sillyfunction(input logic a, b, c,
                     output logic y);

    assign y = ~a & ~b & ~c |
                a & ~b & ~c |
                a & ~b & c;

endmodule

chapter4/example4-1/example4-1.test.sv
// How to run:
// iverilog -o example4-1.out -g2012 example4-1.sv example4-1.test.sv

`timescale 100ns/10ns

module example4_1_testbench;

    // Inputs
    logic a, b, c;

    // Outputs
    logic y;

    // Instantiate the sillyfunction module
    sillyfunction uut (
        .a(a),
        .b(b),
        .c(c),
        .y(y)
    );

    // Initialize inputs
    initial begin
        // 0 - 100 [ns]
        // Input: 0
        a = 0;
        b = 0;
        c = 0;
        #1;
        $display(a, b, c, y);

        // 100 - 200 [ns]
        // Input: 1
        a = 0;
        b = 0;
        c = 1;
        #1;
        $display(a, b, c, y);

        // 200 - 300 [ns]
        // Input: 2
        a = 0;
        b = 1;
        c = 0;
        #1;
        $display(a, b, c, y);

        // 300 - 400 [ns]
        // Input: 3
        a = 0;
        b = 1;
        c = 1;
        #1;
        $display(a, b, c, y);

        // 400 - 500 [ns]
        // Input: 4
        a = 1;
        b = 0;
        c = 0;
        #1;
        $display(a, b, c, y);

        // 500 - 600 [ns]
        // Input: 5
        a = 1;
        b = 0;
        c = 1;
        #1;
        $display(a, b, c, y);

        // 600 - 700 [ns]
        // Input: 6
        a = 1;
        b = 1;
        c = 0;
        #1;
        $display(a, b, c, y);

        // 700 - 800 [ns]
        // Input: 7
        a = 1;
        b = 1;
        c = 1;
        #1;
        $display(a, b, c, y);

        $finish;
    end

    initial begin
        $dumpfile("example4-1.vcd");
        $dumpvars(0, example4_1_testbench);
    end

endmodule

chapter4/example4-1/example4-1.vcd
$date
	Sat Jan 18 19:47:10 2025
$end
$version
	Icarus Verilog
$end
$timescale
	10ns
$end
$scope module example4_1_testbench $end
$var wire 1 ! y $end
$var reg 1 " a $end
$var reg 1 # b $end
$var reg 1 $ c $end
$scope module uut $end
$var wire 1 " a $end
$var wire 1 # b $end
$var wire 1 $ c $end
$var wire 1 ! y $end
$upscope $end
$upscope $end
$enddefinitions $end
$comment Show the parameter values. $end
$dumpall
$end
#0
$dumpvars
0$
0#
0"
1!
$end
#10
0!
1$
#20
0$
1#
#30
1$
#40
1!
0$
0#
1"
#50
1$
#60
0!
0$
1#
#70
1$
